case_changer/__init__.py
case_changer/__main__.py
case_changer/changers.py
case_changer/cli.py
case_changer-0.1.0.dist-info/AUTHORS.rst
case_changer-0.1.0.dist-info/LICENSE
case_changer-0.1.0.dist-info/METADATA
case_changer-0.1.0.dist-info/WHEEL
case_changer-0.1.0.dist-info/entry_points.txt
case_changer-0.1.0.dist-info/top_level.txt
case_changer-0.1.0.dist-info/RECORD
