Metadata-Version: 2.1
Name: case-changer
Version: 0.1.0
Summary: A python port of the npm package `change-case`
Home-page: https://github.com/philipptempel/python-case-changer
Author: Philipp Tempel
Author-email: python@philipptempel.me
License: MIT
Project-URL: Documentation, https://python-case-changer.readthedocs.io/
Project-URL: Changelog, https://python-case-changer.readthedocs.io/en/latest/changelog.html
Project-URL: Issue Tracker, https://github.com/philipptempel/python-case-changer/issues
Keywords: case changer,case conversion,string manipulation
Platform: UNKNOWN
Classifier: Development Status :: 5 - Production/Stable
Classifier: Intended Audience :: Developers
Classifier: License :: OSI Approved :: MIT License
Classifier: Operating System :: Unix
Classifier: Operating System :: POSIX
Classifier: Operating System :: Microsoft :: Windows
Classifier: Programming Language :: Python
Classifier: Programming Language :: Python :: 3
Classifier: Programming Language :: Python :: 3.5
Classifier: Programming Language :: Python :: 3.6
Classifier: Programming Language :: Python :: 3.7
Classifier: Programming Language :: Python :: 3.8
Classifier: Programming Language :: Python :: Implementation :: CPython
Classifier: Programming Language :: Python :: Implementation :: PyPy
Classifier: Topic :: Utilities
Requires-Python: !=2.*, !=3.0.*, !=3.1.*, !=3.2.*, !=3.3.*, !=3.4.*
Requires-Dist: click
